{
	"info": {
		"_postman_id": "e172e471-bf54-4be9-8e8e-8aadad301130",
		"name": "API Testing",
		"schema": "https://schema.getpostman.com/json/collection/v2.1.0/collection.json",
		"_exporter_id": "45867085",
		"_collection_link": "https://anupambhattacharya.postman.co/workspace/Anupam-Bhattacharya's-Workspace~193d935d-73d9-4eac-85dc-91e5ea7a0b65/collection/45867085-e172e471-bf54-4be9-8e8e-8aadad301130?action=share&source=collection_link&creator=45867085"
	},
	"item": [
		{
			"name": "Check JSON Values",
			"request": {
				"method": "GET",
				"header": []
			},
			"response": []
		},
		{
			"name": "Test POST Request",
			"request": {
				"method": "GET",
				"header": []
			},
			"response": []
		}
	]
}
